README.md
setup.py
httpfaker/__init__.py
httpfaker/__main__.py
httpfaker/cli.py
httpfaker.egg-info/PKG-INFO
httpfaker.egg-info/SOURCES.txt
httpfaker.egg-info/dependency_links.txt
httpfaker.egg-info/entry_points.txt
httpfaker.egg-info/requires.txt
httpfaker.egg-info/top_level.txt
httpfaker.egg-info/zip-safe
httpfaker/common/__init__.py
httpfaker/common/database.py
httpfaker/common/db_helper.py
httpfaker/common/drivers.py
httpfaker/common/error.py
httpfaker/common/logger.py
httpfaker/common/setting.py
httpfaker/common/tools.py
httpfaker/utils/Proxy.py
httpfaker/utils/__init__.py
httpfaker/utils/constant.py
httpfaker/utils/faker_date_time.py
httpfaker/utils/faker_tool.py
httpfaker/utils/generator.py
httpfaker/utils/hftest.py
httpfaker/utils/http2api.py
httpfaker/utils/http_mock.py
httpfaker/utils/init_project.py
httpfaker/utils/logic.py
httpfaker/utils/resolve.py
httpfaker/utils/swagger2api.py