Metadata-Version: 2.1
Name: httpfaker
Version: 0.0.5b1216
Summary: 一个无需编写代码的后台服务（mock）
Home-page: https://gitee.com/guojongg/http-faker
Author: Long Guo
Author-email: 565169745@qq.com
License: UNKNOWN
Platform: UNKNOWN
Classifier: Development Status :: 4 - Beta
Classifier: License :: OSI Approved :: BSD License
Classifier: Programming Language :: Python
Classifier: Programming Language :: Python :: 3
Classifier: Programming Language :: Python :: 3.5
Classifier: Programming Language :: Python :: 3.6
Classifier: Programming Language :: Python :: 3.7
Classifier: Topic :: Software Development :: Libraries
